xango/__init__.py
xango/_dict_mutator-next.py
xango/database.py
xango/dict_mutator.py
xango/dict_query.py
xango/exceptions.py
xango/lib.py
xango/lib_dict.py
xango/lib_xgraphql.py
xango/lib_xql.py
xango/lib_xsql.py
xango-0.1.36.dist-info/LICENSE
xango-0.1.36.dist-info/METADATA
xango-0.1.36.dist-info/WHEEL
xango-0.1.36.dist-info/top_level.txt
xango-0.1.36.dist-info/RECORD
