Metadata-Version: 2.1
Name: xango
Version: 0.1.36
Summary: xango
Home-page: https://github.com/mardix/xango
Author: Mardix
Author-email: mardix@blackdevhub.io
Classifier: Programming Language :: Python :: 3
Classifier: License :: OSI Approved :: MIT License
Classifier: Topic :: Database
License-File: LICENSE
Requires-Dist: cuid2
Requires-Dist: arrow
Requires-Dist: sqlglot
Requires-Dist: pydash
Requires-Dist: graphql-core
Requires-Dist: python-slugify
Requires-Dist: Jinja2 >=3.0
Requires-Dist: python-arango ==7.5.8
